simplepay/__init__.py
SimplePay-0.1b0.dist-info/LICENSE
SimplePay-0.1b0.dist-info/METADATA
SimplePay-0.1b0.dist-info/WHEEL
SimplePay-0.1b0.dist-info/top_level.txt
SimplePay-0.1b0.dist-info/RECORD
